squeeze_ctl/__init__.py
squeeze_ctl/ui/__init__.py
squeeze_ctl/ui/cli.py
squeeze_ctl/ui/render.py
squeeze_ctl/ui/tui.py
squeeze_ctl-0.3.2.dist-info/LICENSE
squeeze_ctl-0.3.2.dist-info/METADATA
squeeze_ctl-0.3.2.dist-info/WHEEL
squeeze_ctl-0.3.2.dist-info/entry_points.txt
squeeze_ctl-0.3.2.dist-info/RECORD
