Metadata-Version: 2.1
Name: squeeze-ctl
Version: 0.3.2
Summary: Control your SqueezeBox from the terminal
License: MIT
Author: Simon Redding
Author-email: s1m0n.r3dd1ng@gmail.com
Requires-Python: >=3.11,<4.0
Classifier: License :: OSI Approved :: MIT License
Classifier: Programming Language :: Python :: 3
Classifier: Programming Language :: Python :: 3.11
Requires-Dist: click (>=8.1.7,<9.0.0)
Requires-Dist: requests (>=2.31.0,<3.0.0)
Requires-Dist: squeeze-jrpc (>=0.1.0,<0.2.0)
Requires-Dist: tui-toolkit (>=0.2.1,<0.3.0)
